peasywidgets/__about__.py
peasywidgets/__init__.py
peasywidgets/widgets.py
peasywidgets/py/__init__.py
peasywidgets/py/helpers.py
peasywidgets/static/peasywidgets.css
peasywidgets/static/peasywidgets.js
peasywidgets/templates/datalist.html
peasywidgets-0.2.5.dist-info/METADATA
peasywidgets-0.2.5.dist-info/WHEEL
peasywidgets-0.2.5.dist-info/licenses/LICENSE.txt
peasywidgets-0.2.5.dist-info/RECORD
