Metadata-Version: 2.4
Name: peasywidgets
Version: 0.2.5
Project-URL: Documentation, https://github.com/d-flood/peasywidgets#readme
Project-URL: Issues, https://github.com/d-flood/peasywidgets/issues
Project-URL: Source, https://github.com/d-flood/peasywidgets
Author: d-flood
License-Expression: MIT
License-File: LICENSE.txt
Classifier: Development Status :: 4 - Beta
Classifier: Programming Language :: Python
Classifier: Programming Language :: Python :: 3.10
Classifier: Programming Language :: Python :: 3.11
Classifier: Programming Language :: Python :: 3.12
Classifier: Programming Language :: Python :: Implementation :: CPython
Classifier: Programming Language :: Python :: Implementation :: PyPy
Requires-Python: >=3.10
